thabala_cli/__init__.py
thabala_cli/__main__.py
thabala_cli/cli_parser.py
thabala_cli/configuration.py
thabala_cli/exceptions.py
thabala_cli/logging_config.py
thabala_cli/settings.py
thabala_cli/version.py
thabala_cli/commands/__init__.py
thabala_cli/commands/apply_command.py
thabala_cli/commands/destroy_command.py
thabala_cli/commands/get_command.py
thabala_cli/commands/service_instance_command.py
thabala_cli/commands/version_command.py
thabala_cli/commands/utils/__init__.py
thabala_cli/commands/utils/api_client.py
thabala_cli/commands/utils/auth_base.py
thabala_cli/commands/utils/auth_password.py
thabala_cli/commands/utils/auth_webbrowser.py
thabala_cli/commands/utils/infra_code.py
thabala_cli/commands/utils/profile.py
thabala_cli/config_templates/__init__.py
thabala_cli/config_templates/default_cli.cfg
thabala_cli/config_templates/default_cli_test.cfg
thabala_cli/config_templates/default_cli_user.cfg
thabala_cli/config_templates/thabala_cli_logging_settings.py
thabala_cli/utils/__init__.py
thabala_cli/utils/helpers.py
thabala_cli/utils/module_loading.py
thabala_cli/utils/log/__init__.py
thabala_cli/utils/log/colored_log.py
thabala_cli/utils/log/logging_mixin.py
thabala_cli-1.3.0.dist-info/LICENSE.txt
thabala_cli-1.3.0.dist-info/METADATA
thabala_cli-1.3.0.dist-info/WHEEL
thabala_cli-1.3.0.dist-info/entry_points.txt
thabala_cli-1.3.0.dist-info/top_level.txt
thabala_cli-1.3.0.dist-info/RECORD
