Metadata-Version: 2.1
Name: thabala-cli
Version: 1.3.0
Summary: Thabala Command Line Interface
Home-page: http://github.com/koszti/thabala-cli
Author: Thabala
Classifier: Development Status :: 5 - Production/Stable
Classifier: License :: OSI Approved :: Apache Software License
Classifier: Programming Language :: Python
Classifier: Programming Language :: Python :: 3
Classifier: Programming Language :: Python :: 3.7
Classifier: Programming Language :: Python :: 3.8
Classifier: Programming Language :: Python :: 3.9
Classifier: Programming Language :: Python :: 3.10
Requires-Python: >= 3.7
License-File: LICENSE.txt
Requires-Dist: argcomplete (==2.0.0)
Requires-Dist: colorlog (==6.6.0)
Requires-Dist: pendulum (==2.1.2)
Requires-Dist: pyyaml (==6.0)
Requires-Dist: requests (==2.27.1)
